keras_efficientnets/__init__.py
keras_efficientnets/config.py
keras_efficientnets/custom_objects.py
keras_efficientnets/efficientnet.py
keras_efficientnets/optimize.py
keras_efficientnets-0.1.7.dist-info/LICENSE
keras_efficientnets-0.1.7.dist-info/METADATA
keras_efficientnets-0.1.7.dist-info/WHEEL
keras_efficientnets-0.1.7.dist-info/top_level.txt
keras_efficientnets-0.1.7.dist-info/RECORD
